setup.cfg
setup.py
phovea_data_sql/__init__.py
phovea_data_sql/config.json
phovea_data_sql/sql.py
phovea_data_sql.egg-info/PKG-INFO
phovea_data_sql.egg-info/SOURCES.txt
phovea_data_sql.egg-info/dependency_links.txt
phovea_data_sql.egg-info/entry_points.txt
phovea_data_sql.egg-info/not-zip-safe
phovea_data_sql.egg-info/requires.txt
phovea_data_sql.egg-info/top_level.txt